cshark_kafka/__init__.py
cshark_kafka/cshark_kafka.py
cshark_kafka-0.0.2.dist-info/METADATA
cshark_kafka-0.0.2.dist-info/WHEEL
cshark_kafka-0.0.2.dist-info/top_level.txt
cshark_kafka-0.0.2.dist-info/RECORD
